auto_video_modules/__init__.py
auto_video_modules/audio_utils.py
auto_video_modules/config.py
auto_video_modules/ffmpeg_utils.py
auto_video_modules/gpu_optimization_utils.py
auto_video_modules/mcp_tools.py
auto_video_modules/motion_detection_utils.py
auto_video_modules/subtitle_utils.py
auto_video_modules/video_processing_utils.py
auto_video_modules/video_utils.py
auto_video_modules/voice_utils.py
auto_video_generator_mcp-3.0.0.dist-info/METADATA
auto_video_generator_mcp-3.0.0.dist-info/WHEEL
auto_video_generator_mcp-3.0.0.dist-info/entry_points.txt
auto_video_generator_mcp-3.0.0.dist-info/top_level.txt
auto_video_generator_mcp-3.0.0.dist-info/RECORD
