Metadata-Version: 2.4
Name: auto-video-generator-mcp
Version: 3.0.0
Summary: 基于MCP协议的智能视频生成系统，支持自动添加字幕、语音合成和视频剪辑功能
Home-page: https://github.com/zgmurder/auto_video_generator-mcp
Author: zgmurder
Author-email: zgmurder <zgmurder@example.com>
Maintainer-email: zgmurder <zgmurder@example.com>
License: MIT
Project-URL: Homepage, https://github.com/zgmurder/auto_video_generator-mcp
Project-URL: Documentation, https://github.com/zgmurder/auto_video_generator-mcp#readme
Project-URL: Repository, https://github.com/zgmurder/auto_video_generator-mcp
Project-URL: Bug Tracker, https://github.com/zgmurder/auto_video_generator-mcp/issues
Keywords: video,mcp,subtitle,speech,synthesis,ffmpeg,moviepy
Classifier: Development Status :: 4 - Beta
Classifier: Intended Audience :: Developers
Classifier: License :: OSI Approved :: MIT License
Classifier: Operating System :: OS Independent
Classifier: Programming Language :: Python :: 3
Classifier: Programming Language :: Python :: 3.8
Classifier: Programming Language :: Python :: 3.9
Classifier: Programming Language :: Python :: 3.10
Classifier: Programming Language :: Python :: 3.11
Classifier: Topic :: Multimedia :: Video
Classifier: Topic :: Software Development :: Libraries :: Python Modules
Requires-Python: >=3.8
Requires-Dist: fastmcp>=0.1.0
Requires-Dist: httpx>=0.24.0
Requires-Dist: azure-cognitiveservices-speech>=1.31.0
Requires-Dist: pydub>=0.25.1
Requires-Dist: edge-tts>=6.1.0
Requires-Dist: moviepy==1.0.3
Requires-Dist: opencv-python>=4.8.0
Requires-Dist: imageio-ffmpeg>=0.4.0
Requires-Dist: Pillow>=10.0.0
Requires-Dist: jieba>=0.42.1
Requires-Dist: opencc-python-reimplemented>=0.1.7
Requires-Dist: openai-whisper>=20231117
Requires-Dist: torch>=2.0.0
Requires-Dist: numpy>=1.21.0
Requires-Dist: psutil>=5.9.0
Requires-Dist: tqdm>=4.64.0
Requires-Dist: aiofiles>=0.8.0
Requires-Dist: pydantic>=2.0.0
Requires-Dist: python-dotenv>=1.0.0
Provides-Extra: dev
Requires-Dist: setuptools>=65.0.0; extra == "dev"
Requires-Dist: wheel>=0.37.0; extra == "dev"
Requires-Dist: build>=0.10.0; extra == "dev"
Requires-Dist: twine>=4.0.0; extra == "dev"
Dynamic: author
Dynamic: home-page
Dynamic: requires-python
